ins_nav/__init__.py
ins_nav/calibration/__init__.py
ins_nav/calibration/calaccel.py
ins_nav/calibration/calmag.py
ins_nav/calibration/magplot.py
ins_nav/filters/__init__.py
ins_nav/filters/ahrs.py
ins_nav/filters/compass.py
ins_nav/filters/madgwick.py
ins_nav/filters/mahony.py
ins_nav/nav_frames.py
ins_nav/storage.py
ins_nav/transforms.py
ins_nav/utils.py
ins_nav/wgs84.py
ins_nav-2023.7.2.dist-info/METADATA
ins_nav-2023.7.2.dist-info/WHEEL
ins_nav-2023.7.2.dist-info/RECORD
