Metadata-Version: 2.1
Name: ins-nav
Version: 2023.7.2
Summary: A library to do inertial navigation
Home-page: https://pypi.org/project/ins_nav/
License: MIT
Keywords: library,robotics,robot,ins,inertial,navigation,ahrs,imu
Author: walchko
Author-email: walchko@users.noreply.github.com
Requires-Python: >=3.8
Classifier: Development Status :: 4 - Beta
Classifier: Intended Audience :: Developers
Classifier: License :: OSI Approved :: MIT License
Classifier: Operating System :: OS Independent
Classifier: Programming Language :: Python :: 3
Classifier: Programming Language :: Python :: 3.8
Classifier: Programming Language :: Python :: 3.9
Classifier: Programming Language :: Python :: 3.10
Classifier: Programming Language :: Python :: 3.11
Classifier: Topic :: Software Development :: Libraries
Classifier: Topic :: Software Development :: Libraries :: Application Frameworks
Classifier: Topic :: Software Development :: Libraries :: Python Modules
Requires-Dist: numpy
Requires-Dist: squaternion
Project-URL: Repository, https://github.com/the-guild-of-calamitous-intent/ins_nav
